cdktf_proxmox/__init__.py
cdktf_proxmox/py.typed
cdktf_proxmox/_jsii/__init__.py
cdktf_proxmox/_jsii/cdktf-proxmox@0.0.310.jsii.tgz
cdktf_proxmox/data_proxmox_lvm_storage_classes/__init__.py
cdktf_proxmox/data_proxmox_lvm_thinpool_storage_classes/__init__.py
cdktf_proxmox/data_proxmox_lvm_thinpools/__init__.py
cdktf_proxmox/data_proxmox_lvms/__init__.py
cdktf_proxmox/data_proxmox_network_bonds/__init__.py
cdktf_proxmox/data_proxmox_network_bridges/__init__.py
cdktf_proxmox/data_proxmox_nfs_storage_classes/__init__.py
cdktf_proxmox/data_proxmox_node_storage_lvm_thinpools/__init__.py
cdktf_proxmox/data_proxmox_node_storage_lvms/__init__.py
cdktf_proxmox/data_proxmox_node_storage_nfs/__init__.py
cdktf_proxmox/data_proxmox_node_storage_zfs/__init__.py
cdktf_proxmox/data_proxmox_nodes/__init__.py
cdktf_proxmox/data_proxmox_resource_pools/__init__.py
cdktf_proxmox/data_proxmox_template/__init__.py
cdktf_proxmox/data_proxmox_templates/__init__.py
cdktf_proxmox/data_proxmox_virtual_machines/__init__.py
cdktf_proxmox/data_proxmox_zfs_pools/__init__.py
cdktf_proxmox/data_proxmox_zfs_storage_classes/__init__.py
cdktf_proxmox/lvm/__init__.py
cdktf_proxmox/lvm_storage_class/__init__.py
cdktf_proxmox/lvm_thinpool/__init__.py
cdktf_proxmox/lvm_thinpool_storage_class/__init__.py
cdktf_proxmox/network_bond/__init__.py
cdktf_proxmox/network_bridge/__init__.py
cdktf_proxmox/nfs_storage_class/__init__.py
cdktf_proxmox/provider/__init__.py
cdktf_proxmox/resource_pool/__init__.py
cdktf_proxmox/virtual_machine/__init__.py
cdktf_proxmox/zfs_pool/__init__.py
cdktf_proxmox/zfs_storage_class/__init__.py
cdktf_proxmox-0.0.310.dist-info/LICENSE
cdktf_proxmox-0.0.310.dist-info/METADATA
cdktf_proxmox-0.0.310.dist-info/WHEEL
cdktf_proxmox-0.0.310.dist-info/top_level.txt
cdktf_proxmox-0.0.310.dist-info/RECORD
