Metadata-Version: 2.1
Name: cdktf-proxmox
Version: 0.0.310
Summary: A package that vends generated constructs from the Proxmox Terraform provider
Home-page: https://github.com/awlsring/cdktf-proxmox.git
Author: awlsring<mattcanemail@gmail.com>
License: Apache-2.0
Project-URL: Source, https://github.com/awlsring/cdktf-proxmox.git
Classifier: Intended Audience :: Developers
Classifier: Operating System :: OS Independent
Classifier: Programming Language :: JavaScript
Classifier: Programming Language :: Python :: 3 :: Only
Classifier: Programming Language :: Python :: 3.8
Classifier: Programming Language :: Python :: 3.9
Classifier: Programming Language :: Python :: 3.10
Classifier: Programming Language :: Python :: 3.11
Classifier: Typing :: Typed
Classifier: Development Status :: 5 - Production/Stable
Classifier: License :: OSI Approved
Requires-Python: ~=3.8
License-File: LICENSE
Requires-Dist: cdktf <0.15.0,>=0.14.0
Requires-Dist: constructs <11.0.0,>=10.0.25
Requires-Dist: jsii <2.0.0,>=1.93.0
Requires-Dist: publication >=0.0.3
Requires-Dist: typeguard ~=2.13.3
